config/__init__.py
config/model_config.py
config/presets.py
config/__pycache__/__init__.cpython-38.pyc
config/__pycache__/model_config.cpython-38.pyc
config/__pycache__/presets.cpython-38.pyc
core/__init__.py
core/fused_layer.py
core/model.py
core/__pycache__/__init__.cpython-38.pyc
core/__pycache__/fused_layer.cpython-38.pyc
core/__pycache__/model.cpython-38.pyc
neuratensor/__init__.py
neuratensor/backends.py
neuratensor/cli.py
neuratensor/config.py
neuratensor/demo_sdk_public.py
neuratensor/examples.py
neuratensor/inference.py
neuratensor/model_loader.py
neuratensor/secure_runtime.py
neuratensor/setup.py
neuratensor/tests/__init__.py
neuratensor/tests/test_inference.py
neuratensor/tests/test_model_loader.py
utils/__init__.py
utils/device.py
utils/logger.py
neuratensor-1.1.7.dist-info/LICENSE
neuratensor-1.1.7.dist-info/METADATA
neuratensor-1.1.7.dist-info/WHEEL
neuratensor-1.1.7.dist-info/entry_points.txt
neuratensor-1.1.7.dist-info/top_level.txt
neuratensor-1.1.7.dist-info/RECORD
