Metadata-Version: 2.1
Name: neuratensor
Version: 1.1.7
Summary: Production neuromorphic inference SDK with CUDA acceleration
Home-page: https://neuramorphic.ai
Author: Neuramorphic, Inc.
Author-email: info@neuramorphic.ai
License: Proprietary
Project-URL: Documentation, https://docs.neuramorphic.ai
Project-URL: Source, https://github.com/neuramorphic/neuratensor-sdk
Project-URL: Bug Reports, https://github.com/neuramorphic/neuratensor-sdk/issues
Keywords: neuromorphic,snn,ssm,cuda,inference,deep-learning,ai
Platform: Linux
Classifier: Development Status :: 4 - Beta
Classifier: Intended Audience :: Developers
Classifier: Intended Audience :: Science/Research
Classifier: Topic :: Scientific/Engineering :: Artificial Intelligence
Classifier: License :: Other/Proprietary License
Classifier: Programming Language :: Python :: 3
Classifier: Programming Language :: Python :: 3.8
Classifier: Programming Language :: Python :: 3.9
Classifier: Programming Language :: Python :: 3.10
Classifier: Operating System :: POSIX :: Linux
Classifier: Environment :: GPU :: NVIDIA CUDA
Requires-Python: >=3.8
License-File: LICENSE
Requires-Dist: torch>=2.0.0
Requires-Dist: numpy>=1.19.0
Provides-Extra: cli
Requires-Dist: click>=8.0.0; extra == "cli"
Provides-Extra: dev
Requires-Dist: pytest>=7.0.0; extra == "dev"
Requires-Dist: black>=22.0.0; extra == "dev"
